{"type": "Feature", "id": 12511943, "properties": {"woe:id": 12511943, "woe:parent_id": 2189771, "woe:name": "Minneriya Airport", "woe:placetype": 14, "woe:placetype_name": "Airport", "woe:lang": "ENG", "iso:country": "LK", "meta:provider": ["geoplanet:7.3.1", "geoplanet:7.3.2", "geoplanet:7.4.0", "geoplanet:7.4.1", "geoplanet:7.5.1", "geoplanet:7.5.2", "geoplanet:7.6.0", "geoplanet:7.8.1", "geoplanet:7.9.0", "geoplanet:7.10.0", "geoplanet:8.0.0", "woeplanet:8.0.0"], "meta:indexed": "2020-08-20T20:26:15.013593", "meta:updated": "2020-08-22T01:55:48.316039", "woe:hierarchy": {"continent": 24865671, "country": 23424778, "town": 0, "planet": 1, "county": 23706504, "suburb": 0, "state": 2344960, "region": 0, "localadmin": 0}, "woe:timezone_id": 28350820, "woe:hash": "tc3tfc4hxxu7", "woe:centroid": [80.983299, 8.0483], "geom:latitude": 8.0483, "geom:longitude": 80.983299, "geom:hash": "tc3tfc4hxxu7", "woe:latitude": 8.0483, "geom:centroid": [80.983299, 8.0483], "woe:longitude": 80.983299, "woe:repo": "woeplanet-airport-lk"}, "geometry": {"coordinates": [80.983299, 8.0483], "type": "Point"}}